LICENSE
MANIFEST.in
README.md
requirements-docs.txt
setup.py
wan_account/__init__.py
wan_account/account.py
wan_account/datastructures.py
wan_account/messages.py
wan_account.egg-info/PKG-INFO
wan_account.egg-info/SOURCES.txt
wan_account.egg-info/dependency_links.txt
wan_account.egg-info/not-zip-safe
wan_account.egg-info/requires.txt
wan_account.egg-info/top_level.txt
wan_account/_utils/__init__.py
wan_account/_utils/signing.py
wan_account/_utils/transactions.py
wan_account/_utils/validation.py
wan_account/_utils/structured_data/__init__.py
wan_account/_utils/structured_data/hashing.py
wan_account/_utils/structured_data/validation.py
wan_account/hdaccount/__init__.py
wan_account/hdaccount/_utils.py
wan_account/hdaccount/deterministic.py
wan_account/hdaccount/mnemonic.py
wan_account/hdaccount/wordlist/chinese_simplified.txt
wan_account/hdaccount/wordlist/chinese_traditional.txt
wan_account/hdaccount/wordlist/czech.txt
wan_account/hdaccount/wordlist/english.txt
wan_account/hdaccount/wordlist/french.txt
wan_account/hdaccount/wordlist/italian.txt
wan_account/hdaccount/wordlist/japanese.txt
wan_account/hdaccount/wordlist/korean.txt
wan_account/hdaccount/wordlist/spanish.txt
wan_account/signers/__init__.py
wan_account/signers/base.py
wan_account/signers/local.py