Metadata-Version: 2.1
Name: wan-account
Version: 0.0.3
Summary: wan-account: Sign WanChain transactions and messages with local private keys
Home-page: https://github.com/taobun/wan-account
Author: Bun Uthaitirat
Author-email: taobunoi@gmail.com
License: MIT
Keywords: wanchain
Platform: UNKNOWN
Classifier: Development Status :: 3 - Alpha
Classifier: Intended Audience :: Developers
Classifier: License :: OSI Approved :: MIT License
Classifier: Natural Language :: English
Classifier: Programming Language :: Python :: 3
Classifier: Programming Language :: Python :: 3.6
Classifier: Programming Language :: Python :: 3.7
Classifier: Programming Language :: Python :: 3.8
Requires-Python: >=3.6, <4
Provides-Extra: dev
Provides-Extra: doc
Provides-Extra: lint
Provides-Extra: test
